richcat/__information__.py
richcat/__init__.py
richcat/richcat.py
richcat/modules/__init__.py
richcat/modules/help.py
richcat/modules/utils.py
richcat/modules/consts/__init__.py
richcat/modules/consts/_const.py
richcat/modules/consts/_ext2alias_dic_generator.py
richcat/modules/exceptions/__init__.py
richcat/modules/exceptions/exception.py
richcat/modules/rich_makers/__init__.py
richcat/modules/rich_makers/markdown_maker.py
richcat/modules/rich_makers/syntax_maker.py
richcat/modules/rich_makers/table_maker.py
richcat/modules/rich_makers/template.py
richcat-0.5.0.dist-info/LICENSE
richcat-0.5.0.dist-info/METADATA
richcat-0.5.0.dist-info/WHEEL
richcat-0.5.0.dist-info/entry_points.txt
richcat-0.5.0.dist-info/top_level.txt
richcat-0.5.0.dist-info/RECORD
