Metadata-Version: 2.1
Name: richcat
Version: 0.5.0
Summary: rich cat command working on Python
Home-page: https://github.com/richcat-dev/richcat
Author: Yuta Yamamoto, Shotaro Kataoka
Author-email: automatuX78@gmail.com
License: MIT
Keywords: cat,rich
Platform: UNKNOWN
Classifier: Programming Language :: Python
Classifier: Programming Language :: Python :: 3
Classifier: Programming Language :: Python :: 3.6
Classifier: Programming Language :: Python :: 3.7
Classifier: Programming Language :: Python :: 3.8
Classifier: License :: OSI Approved :: MIT License
Classifier: Operating System :: OS Independent
Requires-Python: >=3.6
Requires-Dist: rich (==11.1.0)
Requires-Dist: sphinx (==4.4.0)
Requires-Dist: sphinx-autobuild (==2021.3.14)
Requires-Dist: sphinx-rtd-theme (==1.0.0)
Requires-Dist: pytest (==6.2.5)
